odoo/addons/sale_order_disable_user_autosubscribe/README.rst
odoo/addons/sale_order_disable_user_autosubscribe/__init__.py
odoo/addons/sale_order_disable_user_autosubscribe/__manifest__.py
odoo/addons/sale_order_disable_user_autosubscribe/i18n/es.po
odoo/addons/sale_order_disable_user_autosubscribe/i18n/it.po
odoo/addons/sale_order_disable_user_autosubscribe/i18n/sale_order_disable_user_autosubscribe.pot
odoo/addons/sale_order_disable_user_autosubscribe/models/__init__.py
odoo/addons/sale_order_disable_user_autosubscribe/models/sale_order.py
odoo/addons/sale_order_disable_user_autosubscribe/readme/CONTRIBUTORS.md
odoo/addons/sale_order_disable_user_autosubscribe/readme/CREDITS.md
odoo/addons/sale_order_disable_user_autosubscribe/readme/DESCRIPTION.md
odoo/addons/sale_order_disable_user_autosubscribe/readme/ROADMAP.md
odoo/addons/sale_order_disable_user_autosubscribe/static/description/icon.png
odoo/addons/sale_order_disable_user_autosubscribe/static/description/index.html
odoo/addons/sale_order_disable_user_autosubscribe/tests/__init__.py
odoo/addons/sale_order_disable_user_autosubscribe/tests/test_sale_order_disable_user_autosubscribe.py
odoo_addon_sale_order_disable_user_autosubscribe-19.0.1.0.0.2.dist-info/METADATA
odoo_addon_sale_order_disable_user_autosubscribe-19.0.1.0.0.2.dist-info/WHEEL
odoo_addon_sale_order_disable_user_autosubscribe-19.0.1.0.0.2.dist-info/top_level.txt
odoo_addon_sale_order_disable_user_autosubscribe-19.0.1.0.0.2.dist-info/RECORD
