Metadata-Version: 2.1
Name: odoo-addon-sale_order_disable_user_autosubscribe
Version: 19.0.1.0.0.2
Requires-Dist: odoo==19.0.*
Summary: Remove the salesperson from autosubscribed sale followers
Home-page: https://github.com/OCA/sale-workflow
License: AGPL-3
Author: Camptocamp SA, Odoo Community Association (OCA)
Author-email: support@odoo-community.org
Classifier: Programming Language :: Python
Classifier: Framework :: Odoo
Classifier: Framework :: Odoo :: 19.0
Classifier: License :: OSI Approved :: GNU Affero General Public License v3
